llama_index/embeddings/sagemaker_endpoint/__init__.py
llama_index/embeddings/sagemaker_endpoint/base.py
llama_index/embeddings/sagemaker_endpoint/utils.py
llama_index_embeddings_sagemaker_endpoint-0.4.1.dist-info/METADATA
llama_index_embeddings_sagemaker_endpoint-0.4.1.dist-info/WHEEL
llama_index_embeddings_sagemaker_endpoint-0.4.1.dist-info/licenses/LICENSE
llama_index_embeddings_sagemaker_endpoint-0.4.1.dist-info/RECORD
